helpers/__init__.py
helpers/__version__.py
helpers/entry_points.py
helpers/models.py
helpers/secret.py
helpers/utils.py
jcHelper/__init__.py
jcHelper/__version__.py
jcHelper/entry_points.py
jcHelper/models.py
jcHelper/secret.py
jcHelper/utils.py
log/__init__.py
log/__version__.py
log/entry_points.py
log/log.py
log/.ipynb_checkpoints/log-checkpoint.py
jchelper_jirawutchayapong-0.0.5.dist-info/LICENSE
jchelper_jirawutchayapong-0.0.5.dist-info/METADATA
jchelper_jirawutchayapong-0.0.5.dist-info/WHEEL
jchelper_jirawutchayapong-0.0.5.dist-info/entry_points.txt
jchelper_jirawutchayapong-0.0.5.dist-info/top_level.txt
jchelper_jirawutchayapong-0.0.5.dist-info/RECORD
