Metadata-Version: 2.1
Name: jchelper-jirawutchayapong
Version: 0.0.5
Summary: jcHelper
Home-page: https://github.com/chayapongjirawut/jchelper
Author: Aey Chayapong
Author-email: chayapongjirawut@gmail.com
License: Apache 2.0
Keywords: jchelper template
Platform: UNKNOWN
Classifier: Development Status :: 4 - Beta
Classifier: Intended Audience :: Developers
Classifier: Programming Language :: Python :: 3.8
Requires-Python: >=3.6.*
Requires-Dist: requests
Requires-Dist: boto3
Requires-Dist: awsSchema
